Workbook

Sheet Plano de Contas
A1: Conta | B1: Descrição da Conta | C1: Nível 1 | D1: Nível 2
A2: 999015461 | B2: Venda de Smart TV 50' 4K | C2: (+) RECEITA BRUTA | D2: 01 - Vendas de Produtos
A3: 999149616 | B3: Venda de iPhone 7 | C3: (+) RECEITA BRUTA | D3: 01 - Vendas de Produtos
A4: 999113857 | B4: Venda de Galaxy S10 | C4: (+) RECEITA BRUTA | D4: 01 - Vendas de Produtos
A5: 999085686 | B5: Venda de Apple Watch | C5: (+) RECEITA BRUTA | D5: 01 - Vendas de Produtos
A6: 999048672 | B6: Venda de Câmera Digital Rebel T6 | C6: (+) RECEITA BRUTA | D6: 01 - Vendas de Produtos
A7: 999040128 | B7: Venda de TV LED 32' | C7: (+) RECEITA BRUTA | D7: 01 - Vendas de Produtos
A8: 999095851 | B8: Venda de Inspiron 15 | C8: (+) RECEITA BRUTA | D8: 01 - Vendas de Produtos
A9: 999081468 | B9: Venda de Smart TV LED Full HD 55' | C9: (+) RECEITA BRUTA | D9: 01 - Vendas de Produtos
A10: 999072838 | B10: Venda de Moto G7 | C10: (+) RECEITA BRUTA | D10: 01 - Vendas de Produtos
A11: 999170260 | B11: Venda de iPhone 6S | C11: (+) RECEITA BRUTA | D11: 01 - Vendas de Produtos
A12: 999090462 | B12: Venda de Tablet M10 Android | C12: (+) RECEITA BRUTA | D12: 01 - Vendas de Produtos
... A141: 999119901 | B141: CONTA XXX.XX.140 | C141: (-) Impostos | D141: 14 - Impostos Federais

Sheet Formato DRE
A1: Ordem | B1: Grupo | C1: Subtotal?
A2: 1 | B2: (+) RECEITA BRUTA | C2: 0
A3: 2 | B3: (-) Deduções da Receita | C3: 0
A4: 3 | B4: (=) RECEITA LÍQUIDA | C4: 1
A5: 4 | B5: (-) Custos de Vendas | C5: 0
A6: 5 | B6: (=) LUCRO BRUTO | C6: 1
A7: 6 | B7: (-) Despesas Gerais | C7: 0
A8: 7 | B8: (-) Impostos | C8: 0
A9: 8 | B9: (=) LUCRO LÍQUIDO | C9: 1

Sheet Orçado
A1: Mês/Ano | B1: Conta | C1: Valor Orçado
A2: 43466 | B2: 999015461 | C2: 924509
A3: 43466 | B3: 999149616 | C3: 808117
A4: 43466 | B4: 999113857 | C4: 380859
A5: 43466 | B5: 999085686 | C5: 691242
A6: 43466 | B6: 999048672 | C6: 585387
A7: 43466 | B7: 999040128 | C7: 429430
A8: 43466 | B8: 999095851 | C8: 403251
A9: 43466 | B9: 999081468 | C9: 632394
A10: 43466 | B10: 999072838 | C10: 826236
A11: 43466 | B11: 999170260 | C11: 386199
A12: 43466 | B12: 999090462 | C12: 878999
A13: 43466 | B13: 999106286 | C13: 666733
... A141: 43466 | B141: 999119901 | C141: -27846
A142: =EDATE(A2,1) -> 43497 | B142: 999015461 | C142: 980743
A143: =EDATE(A3,1) -> 43497 | B143: 999149616 | C143: 224468
A144: =EDATE(A4,1) -> 43497 | B144: 999113857 | C144: 207530
A145: =EDATE(A5,1) -> 43497 | B145: 999085686 | C145: 481795
A146: =EDATE(A6,1) -> 43497 | B146: 999048672 | C146: 887669
A147: =EDATE(A7,1) -> 43497 | B147: 999040128 | C147: 989570
A148: =EDATE(A8,1) -> 43497 | B148: 999095851 | C148: 944968
A149: =EDATE(A9,1) -> 43497 | B149: 999081468 | C149: 909395
A150: =EDATE(A10,1) -> 43497 | B150: 999072838 | C150: 772824
A151: =EDATE(A11,1) -> 43497 | B151: 999170260 | C151: 303480
A152: =EDATE(A12,1) -> 43497 | B152: 999090462 | C152: 921437
A153: =EDATE(A13,1) -> 43497 | B153: 999106286 | C153: 413068
... A1681: =EDATE(A1541,1) -> 43800 | B1681: 999119901 | C1681: -24098

Sheet Orçado Adptado
A1: Mês/Ano | B1: Conta | C1: Valor Orçado | D1: Nível 1 | E1: Nível 2
A2: 43466 | B2: 999015461 | C2: 924509 | D2: =_xlfn.XLOOKUP(fOrcado[[#This Row],[Conta]],'Plano de Contas'!A:A,'Plano de Contas'!C:C) -> (+) RECEITA BRUTA | E2: =_xlfn.XLOOKUP(fOrcado[[#This Row],[Conta]],'Plano de Contas'!A:A,'Plano de Contas'!D:D) -> 01 - Vendas de Produtos
A3: 43466 | B3: 999149616 | C3: 808117 | D3: =_xlfn.XLOOKUP(fOrcado[[#This Row],[Conta]],'Plano de Contas'!A:A,'Plano de Contas'!C:C) -> (+) RECEITA BRUTA | E3: =_xlfn.XLOOKUP(fOrcado[[#This Row],[Conta]],'Plano de Contas'!A:A,'Plano de Contas'!D:D) -> 01 - Vendas de Produtos
A4: 43466 | B4: 999113857 | C4: 380859 | D4: =_xlfn.XLOOKUP(fOrcado[[#This Row],[Conta]],'Plano de Contas'!A:A,'Plano de Contas'!C:C) -> (+) RECEITA BRUTA | E4: =_xlfn.XLOOKUP(fOrcado[[#This Row],[Conta]],'Plano de Contas'!A:A,'Plano de Contas'!D:D) -> 01 - Vendas de Produtos
A5: 43466 | B5: 999085686 | C5: 691242 | D5: =_xlfn.XLOOKUP(fOrcado[[#This Row],[Conta]],'Plano de Contas'!A:A,'Plano de Contas'!C:C) -> (+) RECEITA BRUTA | E5: =_xlfn.XLOOKUP(fOrcado[[#This Row],[Conta]],'Plano de Contas'!A:A,'Plano de Contas'!D:D) -> 01 - Vendas de Produtos
A6: 43466 | B6: 999048672 | C6: 585387 | D6: =_xlfn.XLOOKUP(fOrcado[[#This Row],[Conta]],'Plano de Contas'!A:A,'Plano de Contas'!C:C) -> (+) RECEITA BRUTA | E6: =_xlfn.XLOOKUP(fOrcado[[#This Row],[Conta]],'Plano de Contas'!A:A,'Plano de Contas'!D:D) -> 01 - Vendas de Produtos
A7: 43466 | B7: 999040128 | C7: 429430 | D7: =_xlfn.XLOOKUP(fOrcado[[#This Row],[Conta]],'Plano de Contas'!A:A,'Plano de Contas'!C:C) -> (+) RECEITA BRUTA | E7: =_xlfn.XLOOKUP(fOrcado[[#This Row],[Conta]],'Plano de Contas'!A:A,'Plano de Contas'!D:D) -> 01 - Vendas de Produtos
A8: 43466 | B8: 999095851 | C8: 403251 | D8: =_xlfn.XLOOKUP(fOrcado[[#This Row],[Conta]],'Plano de Contas'!A:A,'Plano de Contas'!C:C) -> (+) RECEITA BRUTA | E8: =_xlfn.XLOOKUP(fOrcado[[#This Row],[Conta]],'Plano de Contas'!A:A,'Plano de Contas'!D:D) -> 01 - Vendas de Produtos
A9: 43466 | B9: 999081468 | C9: 632394 | D9: =_xlfn.XLOOKUP(fOrcado[[#This Row],[Conta]],'Plano de Contas'!A:A,'Plano de Contas'!C:C) -> (+) RECEITA BRUTA | E9: =_xlfn.XLOOKUP(fOrcado[[#This Row],[Conta]],'Plano de Contas'!A:A,'Plano de Contas'!D:D) -> 01 - Vendas de Produtos
A10: 43466 | B10: 999072838 | C10: 826236 | D10: =_xlfn.XLOOKUP(fOrcado[[#This Row],[Conta]],'Plano de Contas'!A:A,'Plano de Contas'!C:C) -> (+) RECEITA BRUTA | E10: =_xlfn.XLOOKUP(fOrcado[[#This Row],[Conta]],'Plano de Contas'!A:A,'Plano de Contas'!D:D) -> 01 - Vendas de Produtos
A11: 43466 | B11: 999170260 | C11: 386199 | D11: =_xlfn.XLOOKUP(fOrcado[[#This Row],[Conta]],'Plano de Contas'!A:A,'Plano de Contas'!C:C) -> (+) RECEITA BRUTA | E11: =_xlfn.XLOOKUP(fOrcado[[#This Row],[Conta]],'Plano de Contas'!A:A,'Plano de Contas'!D:D) -> 01 - Vendas de Produtos
A12: 43466 | B12: 999090462 | C12: 878999 | D12: =_xlfn.XLOOKUP(fOrcado[[#This Row],[Conta]],'Plano de Contas'!A:A,'Plano de Contas'!C:C) -> (+) RECEITA BRUTA | E12: =_xlfn.XLOOKUP(fOrcado[[#This Row],[Conta]],'Plano de Contas'!A:A,'Plano de Contas'!D:D) -> 01 - Vendas de Produtos
A13: 43466 | B13: 999106286 | C13: 666733 | D13: =_xlfn.XLOOKUP(fOrcado[[#This Row],[Conta]],'Plano de Contas'!A:A,'Plano de Contas'!C:C) -> (+) RECEITA BRUTA | E13: =_xlfn.XLOOKUP(fOrcado[[#This Row],[Conta]],'Plano de Contas'!A:A,'Plano de Contas'!D:D) -> 01 - Vendas de Produtos
... A141: 43466 | B141: 999119901 | C141: -27846 | D141: =_xlfn.XLOOKUP(fOrcado[[#This Row],[Conta]],'Plano de Contas'!A:A,'Plano de Contas'!C:C) -> (-) Impostos | E141: =_xlfn.XLOOKUP(fOrcado[[#This Row],[Conta]],'Plano de Contas'!A:A,'Plano de Contas'!D:D) -> 14 - Impostos Federais
A142: =EDATE(A2,1) -> 43497 | B142: 999015461 | C142: 980743 | D142: =_xlfn.XLOOKUP(fOrcado[[#This Row],[Conta]],'Plano de Contas'!A:A,'Plano de Contas'!C:C) -> (+) RECEITA BRUTA | E142: =_xlfn.XLOOKUP(fOrcado[[#This Row],[Conta]],'Plano de Contas'!A:A,'Plano de Contas'!D:D) -> 01 - Vendas de Produtos
A143: =EDATE(A3,1) -> 43497 | B143: 999149616 | C143: 224468 | D143: =_xlfn.XLOOKUP(fOrcado[[#This Row],[Conta]],'Plano de Contas'!A:A,'Plano de Contas'!C:C) -> (+) RECEITA BRUTA | E143: =_xlfn.XLOOKUP(fOrcado[[#This Row],[Conta]],'Plano de Contas'!A:A,'Plano de Contas'!D:D) -> 01 - Vendas de Produtos
A144: =EDATE(A4,1) -> 43497 | B144: 999113857 | C144: 207530 | D144: =_xlfn.XLOOKUP(fOrcado[[#This Row],[Conta]],'Plano de Contas'!A:A,'Plano de Contas'!C:C) -> (+) RECEITA BRUTA | E144: =_xlfn.XLOOKUP(fOrcado[[#This Row],[Conta]],'Plano de Contas'!A:A,'Plano de Contas'!D:D) -> 01 - Vendas de Produtos
A145: =EDATE(A5,1) -> 43497 | B145: 999085686 | C145: 481795 | D145: =_xlfn.XLOOKUP(fOrcado[[#This Row],[Conta]],'Plano de Contas'!A:A,'Plano de Contas'!C:C) -> (+) RECEITA BRUTA | E145: =_xlfn.XLOOKUP(fOrcado[[#This Row],[Conta]],'Plano de Contas'!A:A,'Plano de Contas'!D:D) -> 01 - Vendas de Produtos
A146: =EDATE(A6,1) -> 43497 | B146: 999048672 | C146: 887669 | D146: =_xlfn.XLOOKUP(fOrcado[[#This Row],[Conta]],'Plano de Contas'!A:A,'Plano de Contas'!C:C) -> (+) RECEITA BRUTA | E146: =_xlfn.XLOOKUP(fOrcado[[#This Row],[Conta]],'Plano de Contas'!A:A,'Plano de Contas'!D:D) -> 01 - Vendas de Produtos
A147: =EDATE(A7,1) -> 43497 | B147: 999040128 | C147: 989570 | D147: =_xlfn.XLOOKUP(fOrcado[[#This Row],[Conta]],'Plano de Contas'!A:A,'Plano de Contas'!C:C) -> (+) RECEITA BRUTA | E147: =_xlfn.XLOOKUP(fOrcado[[#This Row],[Conta]],'Plano de Contas'!A:A,'Plano de Contas'!D:D) -> 01 - Vendas de Produtos
A148: =EDATE(A8,1) -> 43497 | B148: 999095851 | C148: 944968 | D148: =_xlfn.XLOOKUP(fOrcado[[#This Row],[Conta]],'Plano de Contas'!A:A,'Plano de Contas'!C:C) -> (+) RECEITA BRUTA | E148: =_xlfn.XLOOKUP(fOrcado[[#This Row],[Conta]],'Plano de Contas'!A:A,'Plano de Contas'!D:D) -> 01 - Vendas de Produtos
A149: =EDATE(A9,1) -> 43497 | B149: 999081468 | C149: 909395 | D149: =_xlfn.XLOOKUP(fOrcado[[#This Row],[Conta]],'Plano de Contas'!A:A,'Plano de Contas'!C:C) -> (+) RECEITA BRUTA | E149: =_xlfn.XLOOKUP(fOrcado[[#This Row],[Conta]],'Plano de Contas'!A:A,'Plano de Contas'!D:D) -> 01 - Vendas de Produtos
A150: =EDATE(A10,1) -> 43497 | B150: 999072838 | C150: 772824 | D150: =_xlfn.XLOOKUP(fOrcado[[#This Row],[Conta]],'Plano de Contas'!A:A,'Plano de Contas'!C:C) -> (+) RECEITA BRUTA | E150: =_xlfn.XLOOKUP(fOrcado[[#This Row],[Conta]],'Plano de Contas'!A:A,'Plano de Contas'!D:D) -> 01 - Vendas de Produtos
A151: =EDATE(A11,1) -> 43497 | B151: 999170260 | C151: 303480 | D151: =_xlfn.XLOOKUP(fOrcado[[#This Row],[Conta]],'Plano de Contas'!A:A,'Plano de Contas'!C:C) -> (+) RECEITA BRUTA | E151: =_xlfn.XLOOKUP(fOrcado[[#This Row],[Conta]],'Plano de Contas'!A:A,'Plano de Contas'!D:D) -> 01 - Vendas de Produtos
A152: =EDATE(A12,1) -> 43497 | B152: 999090462 | C152: 921437 | D152: =_xlfn.XLOOKUP(fOrcado[[#This Row],[Conta]],'Plano de Contas'!A:A,'Plano de Contas'!C:C) -> (+) RECEITA BRUTA | E152: =_xlfn.XLOOKUP(fOrcado[[#This Row],[Conta]],'Plano de Contas'!A:A,'Plano de Contas'!D:D) -> 01 - Vendas de Produtos
A153: =EDATE(A13,1) -> 43497 | B153: 999106286 | C153: 413068 | D153: =_xlfn.XLOOKUP(fOrcado[[#This Row],[Conta]],'Plano de Contas'!A:A,'Plano de Contas'!C:C) -> (+) RECEITA BRUTA | E153: =_xlfn.XLOOKUP(fOrcado[[#This Row],[Conta]],'Plano de Contas'!A:A,'Plano de Contas'!D:D) -> 01 - Vendas de Produtos
... A1681: =EDATE(A1541,1) -> 43800 | B1681: 999119901 | C1681: -24098 | D1681: =_xlfn.XLOOKUP(fOrcado[[#This Row],[Conta]],'Plano de Contas'!A:A,'Plano de Contas'!C:C) -> (-) Impostos | E1681: =_xlfn.XLOOKUP(fOrcado[[#This Row],[Conta]],'Plano de Contas'!A:A,'Plano de Contas'!D:D) -> 14 - Impostos Federais

Sheet Realizado
A1: Mês/Ano | B1: Conta | C1: Valor Realizado
A2: 43466 | B2: 999015461 | C2: 810137
A3: 43466 | B3: 999149616 | C3: 850100
A4: 43466 | B4: 999113857 | C4: 299588
A5: 43466 | B5: 999085686 | C5: 506754
A6: 43466 | B6: 999048672 | C6: 586151
A7: 43466 | B7: 999040128 | C7: 554691
A8: 43466 | B8: 999095851 | C8: 954172
A9: 43466 | B9: 999081468 | C9: 431512
A10: 43466 | B10: 999072838 | C10: 500702
A11: 43466 | B11: 999170260 | C11: 980377
A12: 43466 | B12: 999090462 | C12: 449918
A13: 43466 | B13: 999106286 | C13: 607684
... A141: 43466 | B141: 999119901 | C141: -16645
A142: =EDATE(A2,1) -> 43497 | B142: 999015461 | C142: 936545
A143: =EDATE(A3,1) -> 43497 | B143: 999149616 | C143: 601203
A144: =EDATE(A4,1) -> 43497 | B144: 999113857 | C144: 352326
A145: =EDATE(A5,1) -> 43497 | B145: 999085686 | C145: 656492
A146: =EDATE(A6,1) -> 43497 | B146: 999048672 | C146: 768775
A147: =EDATE(A7,1) -> 43497 | B147: 999040128 | C147: 348586
A148: =EDATE(A8,1) -> 43497 | B148: 999095851 | C148: 549470
A149: =EDATE(A9,1) -> 43497 | B149: 999081468 | C149: 460414
A150: =EDATE(A10,1) -> 43497 | B150: 999072838 | C150: 428915
A151: =EDATE(A11,1) -> 43497 | B151: 999170260 | C151: 645323
A152: =EDATE(A12,1) -> 43497 | B152: 999090462 | C152: 835561
A153: =EDATE(A13,1) -> 43497 | B153: 999106286 | C153: 771550
... A1681: =EDATE(A1541,1) -> 43800 | B1681: 999119901 | C1681: -18108

Sheet Realizado Adptado
A1: Mês/Ano | B1: Conta | C1: Valor Realizado | D1: Nível 1 | E1: Nível 2
A2: 43466 | B2: 999015461 | C2: 810137 | D2: =_xlfn.XLOOKUP(fRealizado5[[#This Row],[Conta]],'Plano de Contas'!A:A,'Plano de Contas'!C:C) -> (+) RECEITA BRUTA | E2: =_xlfn.XLOOKUP(fRealizado5[[#This Row],[Conta]],'Plano de Contas'!A:A,'Plano de Contas'!D:D) -> 01 - Vendas de Produtos
A3: 43466 | B3: 999149616 | C3: 850100 | D3: =_xlfn.XLOOKUP(fRealizado5[[#This Row],[Conta]],'Plano de Contas'!A:A,'Plano de Contas'!C:C) -> (+) RECEITA BRUTA | E3: =_xlfn.XLOOKUP(fRealizado5[[#This Row],[Conta]],'Plano de Contas'!A:A,'Plano de Contas'!D:D) -> 01 - Vendas de Produtos
A4: 43466 | B4: 999113857 | C4: 299588 | D4: =_xlfn.XLOOKUP(fRealizado5[[#This Row],[Conta]],'Plano de Contas'!A:A,'Plano de Contas'!C:C) -> (+) RECEITA BRUTA | E4: =_xlfn.XLOOKUP(fRealizado5[[#This Row],[Conta]],'Plano de Contas'!A:A,'Plano de Contas'!D:D) -> 01 - Vendas de Produtos
A5: 43466 | B5: 999085686 | C5: 506754 | D5: =_xlfn.XLOOKUP(fRealizado5[[#This Row],[Conta]],'Plano de Contas'!A:A,'Plano de Contas'!C:C) -> (+) RECEITA BRUTA | E5: =_xlfn.XLOOKUP(fRealizado5[[#This Row],[Conta]],'Plano de Contas'!A:A,'Plano de Contas'!D:D) -> 01 - Vendas de Produtos
A6: 43466 | B6: 999048672 | C6: 586151 | D6: =_xlfn.XLOOKUP(fRealizado5[[#This Row],[Conta]],'Plano de Contas'!A:A,'Plano de Contas'!C:C) -> (+) RECEITA BRUTA | E6: =_xlfn.XLOOKUP(fRealizado5[[#This Row],[Conta]],'Plano de Contas'!A:A,'Plano de Contas'!D:D) -> 01 - Vendas de Produtos
A7: 43466 | B7: 999040128 | C7: 554691 | D7: =_xlfn.XLOOKUP(fRealizado5[[#This Row],[Conta]],'Plano de Contas'!A:A,'Plano de Contas'!C:C) -> (+) RECEITA BRUTA | E7: =_xlfn.XLOOKUP(fRealizado5[[#This Row],[Conta]],'Plano de Contas'!A:A,'Plano de Contas'!D:D) -> 01 - Vendas de Produtos
A8: 43466 | B8: 999095851 | C8: 954172 | D8: =_xlfn.XLOOKUP(fRealizado5[[#This Row],[Conta]],'Plano de Contas'!A:A,'Plano de Contas'!C:C) -> (+) RECEITA BRUTA | E8: =_xlfn.XLOOKUP(fRealizado5[[#This Row],[Conta]],'Plano de Contas'!A:A,'Plano de Contas'!D:D) -> 01 - Vendas de Produtos
A9: 43466 | B9: 999081468 | C9: 431512 | D9: =_xlfn.XLOOKUP(fRealizado5[[#This Row],[Conta]],'Plano de Contas'!A:A,'Plano de Contas'!C:C) -> (+) RECEITA BRUTA | E9: =_xlfn.XLOOKUP(fRealizado5[[#This Row],[Conta]],'Plano de Contas'!A:A,'Plano de Contas'!D:D) -> 01 - Vendas de Produtos
A10: 43466 | B10: 999072838 | C10: 500702 | D10: =_xlfn.XLOOKUP(fRealizado5[[#This Row],[Conta]],'Plano de Contas'!A:A,'Plano de Contas'!C:C) -> (+) RECEITA BRUTA | E10: =_xlfn.XLOOKUP(fRealizado5[[#This Row],[Conta]],'Plano de Contas'!A:A,'Plano de Contas'!D:D) -> 01 - Vendas de Produtos
A11: 43466 | B11: 999170260 | C11: 980377 | D11: =_xlfn.XLOOKUP(fRealizado5[[#This Row],[Conta]],'Plano de Contas'!A:A,'Plano de Contas'!C:C) -> (+) RECEITA BRUTA | E11: =_xlfn.XLOOKUP(fRealizado5[[#This Row],[Conta]],'Plano de Contas'!A:A,'Plano de Contas'!D:D) -> 01 - Vendas de Produtos
A12: 43466 | B12: 999090462 | C12: 449918 | D12: =_xlfn.XLOOKUP(fRealizado5[[#This Row],[Conta]],'Plano de Contas'!A:A,'Plano de Contas'!C:C) -> (+) RECEITA BRUTA | E12: =_xlfn.XLOOKUP(fRealizado5[[#This Row],[Conta]],'Plano de Contas'!A:A,'Plano de Contas'!D:D) -> 01 - Vendas de Produtos
A13: 43466 | B13: 999106286 | C13: 607684 | D13: =_xlfn.XLOOKUP(fRealizado5[[#This Row],[Conta]],'Plano de Contas'!A:A,'Plano de Contas'!C:C) -> (+) RECEITA BRUTA | E13: =_xlfn.XLOOKUP(fRealizado5[[#This Row],[Conta]],'Plano de Contas'!A:A,'Plano de Contas'!D:D) -> 01 - Vendas de Produtos
... A141: 43466 | B141: 999119901 | C141: -16645 | D141: =_xlfn.XLOOKUP(fRealizado5[[#This Row],[Conta]],'Plano de Contas'!A:A,'Plano de Contas'!C:C) -> (-) Impostos | E141: =_xlfn.XLOOKUP(fRealizado5[[#This Row],[Conta]],'Plano de Contas'!A:A,'Plano de Contas'!D:D) -> 14 - Impostos Federais
A142: =EDATE(A2,1) -> 43497 | B142: 999015461 | C142: 936545 | D142: =_xlfn.XLOOKUP(fRealizado5[[#This Row],[Conta]],'Plano de Contas'!A:A,'Plano de Contas'!C:C) -> (+) RECEITA BRUTA | E142: =_xlfn.XLOOKUP(fRealizado5[[#This Row],[Conta]],'Plano de Contas'!A:A,'Plano de Contas'!D:D) -> 01 - Vendas de Produtos
A143: =EDATE(A3,1) -> 43497 | B143: 999149616 | C143: 601203 | D143: =_xlfn.XLOOKUP(fRealizado5[[#This Row],[Conta]],'Plano de Contas'!A:A,'Plano de Contas'!C:C) -> (+) RECEITA BRUTA | E143: =_xlfn.XLOOKUP(fRealizado5[[#This Row],[Conta]],'Plano de Contas'!A:A,'Plano de Contas'!D:D) -> 01 - Vendas de Produtos
A144: =EDATE(A4,1) -> 43497 | B144: 999113857 | C144: 352326 | D144: =_xlfn.XLOOKUP(fRealizado5[[#This Row],[Conta]],'Plano de Contas'!A:A,'Plano de Contas'!C:C) -> (+) RECEITA BRUTA | E144: =_xlfn.XLOOKUP(fRealizado5[[#This Row],[Conta]],'Plano de Contas'!A:A,'Plano de Contas'!D:D) -> 01 - Vendas de Produtos
A145: =EDATE(A5,1) -> 43497 | B145: 999085686 | C145: 656492 | D145: =_xlfn.XLOOKUP(fRealizado5[[#This Row],[Conta]],'Plano de Contas'!A:A,'Plano de Contas'!C:C) -> (+) RECEITA BRUTA | E145: =_xlfn.XLOOKUP(fRealizado5[[#This Row],[Conta]],'Plano de Contas'!A:A,'Plano de Contas'!D:D) -> 01 - Vendas de Produtos
A146: =EDATE(A6,1) -> 43497 | B146: 999048672 | C146: 768775 | D146: =_xlfn.XLOOKUP(fRealizado5[[#This Row],[Conta]],'Plano de Contas'!A:A,'Plano de Contas'!C:C) -> (+) RECEITA BRUTA | E146: =_xlfn.XLOOKUP(fRealizado5[[#This Row],[Conta]],'Plano de Contas'!A:A,'Plano de Contas'!D:D) -> 01 - Vendas de Produtos
A147: =EDATE(A7,1) -> 43497 | B147: 999040128 | C147: 348586 | D147: =_xlfn.XLOOKUP(fRealizado5[[#This Row],[Conta]],'Plano de Contas'!A:A,'Plano de Contas'!C:C) -> (+) RECEITA BRUTA | E147: =_xlfn.XLOOKUP(fRealizado5[[#This Row],[Conta]],'Plano de Contas'!A:A,'Plano de Contas'!D:D) -> 01 - Vendas de Produtos
A148: =EDATE(A8,1) -> 43497 | B148: 999095851 | C148: 549470 | D148: =_xlfn.XLOOKUP(fRealizado5[[#This Row],[Conta]],'Plano de Contas'!A:A,'Plano de Contas'!C:C) -> (+) RECEITA BRUTA | E148: =_xlfn.XLOOKUP(fRealizado5[[#This Row],[Conta]],'Plano de Contas'!A:A,'Plano de Contas'!D:D) -> 01 - Vendas de Produtos
A149: =EDATE(A9,1) -> 43497 | B149: 999081468 | C149: 460414 | D149: =_xlfn.XLOOKUP(fRealizado5[[#This Row],[Conta]],'Plano de Contas'!A:A,'Plano de Contas'!C:C) -> (+) RECEITA BRUTA | E149: =_xlfn.XLOOKUP(fRealizado5[[#This Row],[Conta]],'Plano de Contas'!A:A,'Plano de Contas'!D:D) -> 01 - Vendas de Produtos
A150: =EDATE(A10,1) -> 43497 | B150: 999072838 | C150: 428915 | D150: =_xlfn.XLOOKUP(fRealizado5[[#This Row],[Conta]],'Plano de Contas'!A:A,'Plano de Contas'!C:C) -> (+) RECEITA BRUTA | E150: =_xlfn.XLOOKUP(fRealizado5[[#This Row],[Conta]],'Plano de Contas'!A:A,'Plano de Contas'!D:D) -> 01 - Vendas de Produtos
A151: =EDATE(A11,1) -> 43497 | B151: 999170260 | C151: 645323 | D151: =_xlfn.XLOOKUP(fRealizado5[[#This Row],[Conta]],'Plano de Contas'!A:A,'Plano de Contas'!C:C) -> (+) RECEITA BRUTA | E151: =_xlfn.XLOOKUP(fRealizado5[[#This Row],[Conta]],'Plano de Contas'!A:A,'Plano de Contas'!D:D) -> 01 - Vendas de Produtos
A152: =EDATE(A12,1) -> 43497 | B152: 999090462 | C152: 835561 | D152: =_xlfn.XLOOKUP(fRealizado5[[#This Row],[Conta]],'Plano de Contas'!A:A,'Plano de Contas'!C:C) -> (+) RECEITA BRUTA | E152: =_xlfn.XLOOKUP(fRealizado5[[#This Row],[Conta]],'Plano de Contas'!A:A,'Plano de Contas'!D:D) -> 01 - Vendas de Produtos
A153: =EDATE(A13,1) -> 43497 | B153: 999106286 | C153: 771550 | D153: =_xlfn.XLOOKUP(fRealizado5[[#This Row],[Conta]],'Plano de Contas'!A:A,'Plano de Contas'!C:C) -> (+) RECEITA BRUTA | E153: =_xlfn.XLOOKUP(fRealizado5[[#This Row],[Conta]],'Plano de Contas'!A:A,'Plano de Contas'!D:D) -> 01 - Vendas de Produtos
... A1681: =EDATE(A1541,1) -> 43800 | B1681: 999119901 | C1681: -18108 | D1681: =_xlfn.XLOOKUP(fRealizado5[[#This Row],[Conta]],'Plano de Contas'!A:A,'Plano de Contas'!C:C) -> (-) Impostos | E1681: =_xlfn.XLOOKUP(fRealizado5[[#This Row],[Conta]],'Plano de Contas'!A:A,'Plano de Contas'!D:D) -> 14 - Impostos Federais

Sheet FINANCEIRO
A1: MÊS | B1: RECEITA BRUTA | C1: DEDUÇÕES DA RECEITA | D1: RECEITA LÍQUIDA | E1: CUSTOS | F1: LUCRO BRUTO | G1: DESPESAS GERAIS | H1: IMPOSTOS | I1: LUCRO LÍQUIDO
A2: 43466 | B2: =SUMIFS('Realizado Adptado'!C:C,'Realizado Adptado'!D:D,fRealizado5[[#This Row],[Nível 1]],'Realizado Adptado'!A:A,FINANCEIRO!A2) -> 20050916 | C2: =SUMIFS('Realizado Adptado'!C:C,'Realizado Adptado'!D:D,'Realizado Adptado'!$D$77,'Realizado Adptado'!A:A,FINANCEIRO!A2) -> -185098 | D2: =B2+C2 -> 19865818 | E2: =SUMIFS('Realizado Adptado'!C:C,'Realizado Adptado'!D:D,'Realizado Adptado'!$D$91,'Realizado Adptado'!A:A,FINANCEIRO!A2) -> -4915811 | F2: =D2+E2 -> 14950007 | G2: =SUMIFS('Realizado Adptado'!C:C,'Realizado Adptado'!D:D,'Realizado Adptado'!$D$118,'Realizado Adptado'!A:A,FINANCEIRO!A2) -> -3284072 | H2: =SUMIFS('Realizado Adptado'!C:C,'Realizado Adptado'!D:D,'Realizado Adptado'!$D$140,'Realizado Adptado'!A:A,FINANCEIRO!A2) -> -24897 | I2: =F2+G2+H2 -> 11641038
A3: 43497 | B3: =SUMIFS('Realizado Adptado'!C:C,'Realizado Adptado'!D:D,fRealizado5[[#This Row],[Nível 1]],'Realizado Adptado'!A:A,FINANCEIRO!A3) -> 19648815 | C3: =SUMIFS('Realizado Adptado'!C:C,'Realizado Adptado'!D:D,'Realizado Adptado'!$D$77,'Realizado Adptado'!A:A,FINANCEIRO!A3) -> -168252 | D3: =B3+C3 -> 19480563 | E3: =SUMIFS('Realizado Adptado'!C:C,'Realizado Adptado'!D:D,'Realizado Adptado'!$D$91,'Realizado Adptado'!A:A,FINANCEIRO!A3) -> -5221289 | F3: =D3+E3 -> 14259274 | G3: =SUMIFS('Realizado Adptado'!C:C,'Realizado Adptado'!D:D,'Realizado Adptado'!$D$118,'Realizado Adptado'!A:A,FINANCEIRO!A3) -> -3189018 | H3: =SUMIFS('Realizado Adptado'!C:C,'Realizado Adptado'!D:D,'Realizado Adptado'!$D$140,'Realizado Adptado'!A:A,FINANCEIRO!A3) -> -38811 | I3: =F3+G3+H3 -> 11031445
A4: 43525 | B4: =SUMIFS('Realizado Adptado'!C:C,'Realizado Adptado'!D:D,fRealizado5[[#This Row],[Nível 1]],'Realizado Adptado'!A:A,FINANCEIRO!A4) -> 21095352 | C4: =SUMIFS('Realizado Adptado'!C:C,'Realizado Adptado'!D:D,'Realizado Adptado'!$D$77,'Realizado Adptado'!A:A,FINANCEIRO!A4) -> -145910 | D4: =B4+C4 -> 20949442 | E4: =SUMIFS('Realizado Adptado'!C:C,'Realizado Adptado'!D:D,'Realizado Adptado'!$D$91,'Realizado Adptado'!A:A,FINANCEIRO!A4) -> -4718093 | F4: =D4+E4 -> 16231349 | G4: =SUMIFS('Realizado Adptado'!C:C,'Realizado Adptado'!D:D,'Realizado Adptado'!$D$118,'Realizado Adptado'!A:A,FINANCEIRO!A4) -> -3217161 | H4: =SUMIFS('Realizado Adptado'!C:C,'Realizado Adptado'!D:D,'Realizado Adptado'!$D$140,'Realizado Adptado'!A:A,FINANCEIRO!A4) -> -35250 | I4: =F4+G4+H4 -> 12978938
A5: 43556 | B5: =SUMIFS('Realizado Adptado'!C:C,'Realizado Adptado'!D:D,fRealizado5[[#This Row],[Nível 1]],'Realizado Adptado'!A:A,FINANCEIRO!A5) -> 19936804 | C5: =SUMIFS('Realizado Adptado'!C:C,'Realizado Adptado'!D:D,'Realizado Adptado'!$D$77,'Realizado Adptado'!A:A,FINANCEIRO!A5) -> -173600 | D5: =B5+C5 -> 19763204 | E5: =SUMIFS('Realizado Adptado'!C:C,'Realizado Adptado'!D:D,'Realizado Adptado'!$D$91,'Realizado Adptado'!A:A,FINANCEIRO!A5) -> -4580143 | F5: =D5+E5 -> 15183061 | G5: =SUMIFS('Realizado Adptado'!C:C,'Realizado Adptado'!D:D,'Realizado Adptado'!$D$118,'Realizado Adptado'!A:A,FINANCEIRO!A5) -> -2561595 | H5: =SUMIFS('Realizado Adptado'!C:C,'Realizado Adptado'!D:D,'Realizado Adptado'!$D$140,'Realizado Adptado'!A:A,FINANCEIRO!A5) -> -32089 | I5: =F5+G5+H5 -> 12589377
A6: 43586 | B6: =SUMIFS('Realizado Adptado'!C:C,'Realizado Adptado'!D:D,fRealizado5[[#This Row],[Nível 1]],'Realizado Adptado'!A:A,FINANCEIRO!A6) -> 17462474 | C6: =SUMIFS('Realizado Adptado'!C:C,'Realizado Adptado'!D:D,'Realizado Adptado'!$D$77,'Realizado Adptado'!A:A,FINANCEIRO!A6) -> -165992 | D6: =B6+C6 -> 17296482 | E6: =SUMIFS('Realizado Adptado'!C:C,'Realizado Adptado'!D:D,'Realizado Adptado'!$D$91,'Realizado Adptado'!A:A,FINANCEIRO!A6) -> -5140114 | F6: =D6+E6 -> 12156368 | G6: =SUMIFS('Realizado Adptado'!C:C,'Realizado Adptado'!D:D,'Realizado Adptado'!$D$118,'Realizado Adptado'!A:A,FINANCEIRO!A6) -> -3614244 | H6: =SUMIFS('Realizado Adptado'!C:C,'Realizado Adptado'!D:D,'Realizado Adptado'!$D$140,'Realizado Adptado'!A:A,FINANCEIRO!A6) -> -32971 | I6: =F6+G6+H6 -> 8509153
A7: 43617 | B7: =SUMIFS('Realizado Adptado'!C:C,'Realizado Adptado'!D:D,fRealizado5[[#This Row],[Nível 1]],'Realizado Adptado'!A:A,FINANCEIRO!A7) -> 19786714 | C7: =SUMIFS('Realizado Adptado'!C:C,'Realizado Adptado'!D:D,'Realizado Adptado'!$D$77,'Realizado Adptado'!A:A,FINANCEIRO!A7) -> -159033 | D7: =B7+C7 -> 19627681 | E7: =SUMIFS('Realizado Adptado'!C:C,'Realizado Adptado'!D:D,'Realizado Adptado'!$D$91,'Realizado Adptado'!A:A,FINANCEIRO!A7) -> -4889543 | F7: =D7+E7 -> 14738138 | G7: =SUMIFS('Realizado Adptado'!C:C,'Realizado Adptado'!D:D,'Realizado Adptado'!$D$118,'Realizado Adptado'!A:A,FINANCEIRO!A7) -> -3150549 | H7: =SUMIFS('Realizado Adptado'!C:C,'Realizado Adptado'!D:D,'Realizado Adptado'!$D$140,'Realizado Adptado'!A:A,FINANCEIRO!A7) -> -39678 | I7: =F7+G7+H7 -> 11547911
A8: 43647 | B8: =SUMIFS('Realizado Adptado'!C:C,'Realizado Adptado'!D:D,fRealizado5[[#This Row],[Nível 1]],'Realizado Adptado'!A:A,FINANCEIRO!A8) -> 20728326 | C8: =SUMIFS('Realizado Adptado'!C:C,'Realizado Adptado'!D:D,'Realizado Adptado'!$D$77,'Realizado Adptado'!A:A,FINANCEIRO!A8) -> -159948 | D8: =B8+C8 -> 20568378 | E8: =SUMIFS('Realizado Adptado'!C:C,'Realizado Adptado'!D:D,'Realizado Adptado'!$D$91,'Realizado Adptado'!A:A,FINANCEIRO!A8) -> -4180486 | F8: =D8+E8 -> 16387892 | G8: =SUMIFS('Realizado Adptado'!C:C,'Realizado Adptado'!D:D,'Realizado Adptado'!$D$118,'Realizado Adptado'!A:A,FINANCEIRO!A8) -> -3134958 | H8: =SUMIFS('Realizado Adptado'!C:C,'Realizado Adptado'!D:D,'Realizado Adptado'!$D$140,'Realizado Adptado'!A:A,FINANCEIRO!A8) -> -31127 | I8: =F8+G8+H8 -> 13221807
A9: 43678 | B9: =SUMIFS('Realizado Adptado'!C:C,'Realizado Adptado'!D:D,fRealizado5[[#This Row],[Nível 1]],'Realizado Adptado'!A:A,FINANCEIRO!A9) -> 21262064 | C9: =SUMIFS('Realizado Adptado'!C:C,'Realizado Adptado'!D:D,'Realizado Adptado'!$D$77,'Realizado Adptado'!A:A,FINANCEIRO!A9) -> -180363 | D9: =B9+C9 -> 21081701 | E9: =SUMIFS('Realizado Adptado'!C:C,'Realizado Adptado'!D:D,'Realizado Adptado'!$D$91,'Realizado Adptado'!A:A,FINANCEIRO!A9) -> -4912768 | F9: =D9+E9 -> 16168933 | G9: =SUMIFS('Realizado Adptado'!C:C,'Realizado Adptado'!D:D,'Realizado Adptado'!$D$118,'Realizado Adptado'!A:A,FINANCEIRO!A9) -> -3040090 | H9: =SUMIFS('Realizado Adptado'!C:C,'Realizado Adptado'!D:D,'Realizado Adptado'!$D$140,'Realizado Adptado'!A:A,FINANCEIRO!A9) -> -29301 | I9: =F9+G9+H9 -> 13099542
A10: 43709 | B10: =SUMIFS('Realizado Adptado'!C:C,'Realizado Adptado'!D:D,fRealizado5[[#This Row],[Nível 1]],'Realizado Adptado'!A:A,FINANCEIRO!A10) -> 21001843 | C10: =SUMIFS('Realizado Adptado'!C:C,'Realizado Adptado'!D:D,'Realizado Adptado'!$D$77,'Realizado Adptado'!A:A,FINANCEIRO!A10) -> -167665 | D10: =B10+C10 -> 20834178 | E10: =SUMIFS('Realizado Adptado'!C:C,'Realizado Adptado'!D:D,'Realizado Adptado'!$D$91,'Realizado Adptado'!A:A,FINANCEIRO!A10) -> -4944455 | F10: =D10+E10 -> 15889723 | G10: =SUMIFS('Realizado Adptado'!C:C,'Realizado Adptado'!D:D,'Realizado Adptado'!$D$118,'Realizado Adptado'!A:A,FINANCEIRO!A10) -> -2640349 | H10: =SUMIFS('Realizado Adptado'!C:C,'Realizado Adptado'!D:D,'Realizado Adptado'!$D$140,'Realizado Adptado'!A:A,FINANCEIRO!A10) -> -38038 | I10: =F10+G10+H10 -> 13211336
A11: 43739 | B11: =SUMIFS('Realizado Adptado'!C:C,'Realizado Adptado'!D:D,fRealizado5[[#This Row],[Nível 1]],'Realizado Adptado'!A:A,FINANCEIRO!A11) -> 19216027 | C11: =SUMIFS('Realizado Adptado'!C:C,'Realizado Adptado'!D:D,'Realizado Adptado'!$D$77,'Realizado Adptado'!A:A,FINANCEIRO!A11) -> -153051 | D11: =B11+C11 -> 19062976 | E11: =SUMIFS('Realizado Adptado'!C:C,'Realizado Adptado'!D:D,'Realizado Adptado'!$D$91,'Realizado Adptado'!A:A,FINANCEIRO!A11) -> -4480907 | F11: =D11+E11 -> 14582069 | G11: =SUMIFS('Realizado Adptado'!C:C,'Realizado Adptado'!D:D,'Realizado Adptado'!$D$118,'Realizado Adptado'!A:A,FINANCEIRO!A11) -> -3195547 | H11: =SUMIFS('Realizado Adptado'!C:C,'Realizado Adptado'!D:D,'Realizado Adptado'!$D$140,'Realizado Adptado'!A:A,FINANCEIRO!A11) -> -27175 | I11: =F11+G11+H11 -> 11359347
A12: 43770 | B12: =SUMIFS('Realizado Adptado'!C:C,'Realizado Adptado'!D:D,fRealizado5[[#This Row],[Nível 1]],'Realizado Adptado'!A:A,FINANCEIRO!A12) -> 19431711 | C12: =SUMIFS('Realizado Adptado'!C:C,'Realizado Adptado'!D:D,'Realizado Adptado'!$D$77,'Realizado Adptado'!A:A,FINANCEIRO!A12) -> -187203 | D12: =B12+C12 -> 19244508 | E12: =SUMIFS('Realizado Adptado'!C:C,'Realizado Adptado'!D:D,'Realizado Adptado'!$D$91,'Realizado Adptado'!A:A,FINANCEIRO!A12) -> -4472333 | F12: =D12+E12 -> 14772175 | G12: =SUMIFS('Realizado Adptado'!C:C,'Realizado Adptado'!D:D,'Realizado Adptado'!$D$118,'Realizado Adptado'!A:A,FINANCEIRO!A12) -> -3378288 | H12: =SUMIFS('Realizado Adptado'!C:C,'Realizado Adptado'!D:D,'Realizado Adptado'!$D$140,'Realizado Adptado'!A:A,FINANCEIRO!A12) -> -34834 | I12: =F12+G12+H12 -> 11359053
A13: 43800 | B13: =SUMIFS('Realizado Adptado'!C:C,'Realizado Adptado'!D:D,fRealizado5[[#This Row],[Nível 1]],'Realizado Adptado'!A:A,FINANCEIRO!A13) -> 21131071 | C13: =SUMIFS('Realizado Adptado'!C:C,'Realizado Adptado'!D:D,'Realizado Adptado'!$D$77,'Realizado Adptado'!A:A,FINANCEIRO!A13) -> -170427 | D13: =B13+C13 -> 20960644 | E13: =SUMIFS('Realizado Adptado'!C:C,'Realizado Adptado'!D:D,'Realizado Adptado'!$D$91,'Realizado Adptado'!A:A,FINANCEIRO!A13) -> -4619555 | F13: =D13+E13 -> 16341089 | G13: =SUMIFS('Realizado Adptado'!C:C,'Realizado Adptado'!D:D,'Realizado Adptado'!$D$118,'Realizado Adptado'!A:A,FINANCEIRO!A13) -> -3259149 | H13: =SUMIFS('Realizado Adptado'!C:C,'Realizado Adptado'!D:D,'Realizado Adptado'!$D$140,'Realizado Adptado'!A:A,FINANCEIRO!A13) -> -27796 | I13: =F13+G13+H13 -> 13054144
A19: MÊS | B19: % DEDUÇÕES | C19: % CUSTOS | D19: % DESPESAS | E19: % IMPOSTOS | F19: MARGEM BRUTA | G19: MARGEM LÍQUIDA
A20: 43466 | B20: =C2/D2 -> -0.0093174114 | C20: =E2/D2 -> -0.24745072 | D20: =G2/D2 -> -0.1653127 | E20: =H2/D2 -> -0.0012532582 | F20: =F2/D2 -> 0.75254928 | G20: =I2/D2 -> 0.58598332
A21: 43497 | B21: =C3/D3 -> -0.0086369167 | C21: =E3/D3 -> -0.26802557 | D21: =G3/D3 -> -0.16370256 | E21: =H3/D3 -> -0.0019922935 | F21: =F3/D3 -> 0.73197443 | G21: =I3/D3 -> 0.56627958
A22: 43525 | B22: =C4/D4 -> -0.0069648633 | C22: =E4/D4 -> -0.2252133 | D22: =G4/D4 -> -0.15356786 | E22: =H4/D4 -> -0.0016826224 | F22: =F4/D4 -> 0.7747867 | G22: =I4/D4 -> 0.61953621
A23: 43556 | B23: =C5/D5 -> -0.0087840008 | C23: =E5/D5 -> -0.23175104 | D23: =G5/D5 -> -0.12961436 | E23: =H5/D5 -> -0.001623674 | F23: =F5/D5 -> 0.76824896 | G23: =I5/D5 -> 0.63701093
A24: 43586 | B24: =C6/D6 -> -0.0095968648 | C24: =E6/D6 -> -0.29717685 | D24: =G6/D6 -> -0.20895833 | E24: =H6/D6 -> -0.0019062258 | F24: =F6/D6 -> 0.70282315 | G24: =I6/D6 -> 0.4919586
A25: 43617 | B25: =C7/D7 -> -0.0081024855 | C25: =E7/D7 -> -0.24911466 | D25: =G7/D7 -> -0.1605156 | E25: =H7/D7 -> -0.0020215328 | F25: =F7/D7 -> 0.75088534 | G25: =I7/D7 -> 0.58834821
A26: 43647 | B26: =C8/D8 -> -0.0077764032 | C26: =E8/D8 -> -0.20324821 | D26: =G8/D8 -> -0.15241639 | E26: =H8/D8 -> -0.0015133425 | F26: =F8/D8 -> 0.79675179 | G26: =I8/D8 -> 0.64282205
A27: 43678 | B27: =C9/D9 -> -0.0085554292 | C27: =E9/D9 -> -0.23303471 | D27: =G9/D9 -> -0.14420516 | E27: =H9/D9 -> -0.0013898784 | F27: =F9/D9 -> 0.76696529 | G27: =I9/D9 -> 0.62137026
A28: 43709 | B28: =C10/D10 -> -0.0080475937 | C28: =E10/D10 -> -0.23732422 | D28: =G10/D10 -> -0.12673161 | E28: =H10/D10 -> -0.00182575 | F28: =F10/D10 -> 0.76267578 | G28: =I10/D10 -> 0.63411842
A29: 43739 | B29: =C11/D11 -> -0.0080287044 | C29: =E11/D11 -> -0.2350581 | D29: =G11/D11 -> -0.16763107 | E29: =H11/D11 -> -0.0014255382 | F29: =F11/D11 -> 0.7649419 | G29: =I11/D11 -> 0.59588529
A30: 43770 | B30: =C12/D12 -> -0.0097276064 | C30: =E12/D12 -> -0.23239529 | D30: =G12/D12 -> -0.17554556 | E30: =H12/D12 -> -0.0018100749 | F30: =F12/D12 -> 0.76760471 | G30: =I12/D12 -> 0.59024907
A31: 43800 | B31: =C13/D13 -> -0.0081308093 | C31: =E13/D13 -> -0.22039184 | D31: =G13/D13 -> -0.15548897 | E31: =H13/D13 -> -0.0013261043 | F31: =F13/D13 -> 0.77960816 | G31: =I13/D13 -> 0.62279308

Sheet DASHBOARD
A1: RECEITA BRUTA | B1: DEDUÇÕES DA RECEITA | C1: RECEITA LÍQUIDA | D1: CUSTOS | E1: LUCRO BRUTO | F1: DESPESAS GERAIS | G1: IMPOSTOS | H1: LUCRO LÍQUIDO | I1: L.LÍQUIDO MENSAL
A6: =SUM(FINANCEIRO!B2:B13) -> 240752117 | B6: =SUM(FINANCEIRO!C2:C13) -> -2016542 | C6: =SUM(FINANCEIRO!D2:D13) -> 238735575 | D6: =SUM(FINANCEIRO!E2:E13) -> -57075497 | E6: =SUM(FINANCEIRO!F2:F13) -> 181660078 | F6: =SUM(FINANCEIRO!G2:G13) -> -37665020 | G6: =SUM(FINANCEIRO!H2:H13) -> -391967 | H6: =SUM(FINANCEIRO!I2:I13) -> 143603091 | I6: =AVERAGE(FINANCEIRO!I2:I13) -> 11966924

Sheet ORÇAMENTO
A1: Mês/Ano | B1: Valor Orçado | C1: Valor Realizado | D1: Desvio Absoluto | E1: Desvio % | H1: Conta | I1: Descrição da Conta | J1: Valor Orçado | K1: Valor Realizado | L1: Desvio Absoluto | M1: Desvio %
A2: 43466 | B2: =SUMIF('Orçado Adptado'!A:A,Tabela8[[#This Row],[Mês/Ano]],'Orçado Adptado'!C:C) -> 12628342 | C2: =SUMIF(Realizado!A:A,Tabela8[[#This Row],[Mês/Ano]],Realizado!C:C) -> 11641038 | D2: =Tabela8[[#This Row],[Valor Realizado]]-Tabela8[[#This Row],[Valor Orçado]] -> -987304 | E2: =ABS((Tabela8[[#This Row],[Valor Realizado]]-Tabela8[[#This Row],[Valor Orçado]])/Tabela8[[#This Row],[Valor Orçado]]) -> 0.078181601 | H2: 999015461 | I2: Venda de Smart TV 50' 4K | J2: =SUMIF('Orçado Adptado'!B:B,ORÇAMENTO!H2,'Orçado Adptado'!C:C) -> 8701733 | K2: =SUMIF(Realizado!B:B,ORÇAMENTO!H2,Realizado!C:C) -> 7791574 | L2: =K2-J2 -> -910159 | M2: =ABS((K2-J2)/J2) -> 0.10459514
A3: 43497 | B3: =SUMIF('Orçado Adptado'!A:A,Tabela8[[#This Row],[Mês/Ano]],'Orçado Adptado'!C:C) -> 12787711 | C3: =SUMIF(Realizado!A:A,Tabela8[[#This Row],[Mês/Ano]],Realizado!C:C) -> 11031445 | D3: =Tabela8[[#This Row],[Valor Realizado]]-Tabela8[[#This Row],[Valor Orçado]] -> -1756266 | E3: =ABS((Tabela8[[#This Row],[Valor Realizado]]-Tabela8[[#This Row],[Valor Orçado]])/Tabela8[[#This Row],[Valor Orçado]]) -> 0.13734014 | H3: 999149616 | I3: Venda de iPhone 7 | J3: =SUMIF('Orçado Adptado'!B:B,ORÇAMENTO!H3,'Orçado Adptado'!C:C) -> 5786342 | K3: =SUMIF(Realizado!B:B,ORÇAMENTO!H3,Realizado!C:C) -> 7768159 | L3: =K3-J3 -> 1981817 | M3: =ABS((K3-J3)/J3) -> 0.34249911
A4: 43525 | B4: =SUMIF('Orçado Adptado'!A:A,Tabela8[[#This Row],[Mês/Ano]],'Orçado Adptado'!C:C) -> 14186373 | C4: =SUMIF(Realizado!A:A,Tabela8[[#This Row],[Mês/Ano]],Realizado!C:C) -> 12978938 | D4: =Tabela8[[#This Row],[Valor Realizado]]-Tabela8[[#This Row],[Valor Orçado]] -> -1207435 | E4: =ABS((Tabela8[[#This Row],[Valor Realizado]]-Tabela8[[#This Row],[Valor Orçado]])/Tabela8[[#This Row],[Valor Orçado]]) -> 0.085112312 | H4: 999113857 | I4: Venda de Galaxy S10 | J4: =SUMIF('Orçado Adptado'!B:B,ORÇAMENTO!H4,'Orçado Adptado'!C:C) -> 5564830 | K4: =SUMIF(Realizado!B:B,ORÇAMENTO!H4,Realizado!C:C) -> 7368112 | L4: =K4-J4 -> 1803282 | M4: =ABS((K4-J4)/J4) -> 0.32404979
A5: 43556 | B5: =SUMIF('Orçado Adptado'!A:A,Tabela8[[#This Row],[Mês/Ano]],'Orçado Adptado'!C:C) -> 9555695 | C5: =SUMIF(Realizado!A:A,Tabela8[[#This Row],[Mês/Ano]],Realizado!C:C) -> 12589377 | D5: =Tabela8[[#This Row],[Valor Realizado]]-Tabela8[[#This Row],[Valor Orçado]] -> 3033682 | E5: =ABS((Tabela8[[#This Row],[Valor Realizado]]-Tabela8[[#This Row],[Valor Orçado]])/Tabela8[[#This Row],[Valor Orçado]]) -> 0.31747372 | H5: 999085686 | I5: Venda de Apple Watch | J5: =SUMIF('Orçado Adptado'!B:B,ORÇAMENTO!H5,'Orçado Adptado'!C:C) -> 6741887 | K5: =SUMIF(Realizado!B:B,ORÇAMENTO!H5,Realizado!C:C) -> 8291974 | L5: =K5-J5 -> 1550087 | M5: =ABS((K5-J5)/J5) -> 0.22991886
A6: 43586 | B6: =SUMIF('Orçado Adptado'!A:A,Tabela8[[#This Row],[Mês/Ano]],'Orçado Adptado'!C:C) -> 11240344 | C6: =SUMIF(Realizado!A:A,Tabela8[[#This Row],[Mês/Ano]],Realizado!C:C) -> 8509153 | D6: =Tabela8[[#This Row],[Valor Realizado]]-Tabela8[[#This Row],[Valor Orçado]] -> -2731191 | E6: =ABS((Tabela8[[#This Row],[Valor Realizado]]-Tabela8[[#This Row],[Valor Orçado]])/Tabela8[[#This Row],[Valor Orçado]]) -> 0.24298109 | H6: 999048672 | I6: Venda de Câmera Digital Rebel T6 | J6: =SUMIF('Orçado Adptado'!B:B,ORÇAMENTO!H6,'Orçado Adptado'!C:C) -> 9282137 | K6: =SUMIF(Realizado!B:B,ORÇAMENTO!H6,Realizado!C:C) -> 8563185 | L6: =K6-J6 -> -718952 | M6: =ABS((K6-J6)/J6) -> 0.077455439
A7: 43617 | B7: =SUMIF('Orçado Adptado'!A:A,Tabela8[[#This Row],[Mês/Ano]],'Orçado Adptado'!C:C) -> 11922744 | C7: =SUMIF(Realizado!A:A,Tabela8[[#This Row],[Mês/Ano]],Realizado!C:C) -> 11547911 | D7: =Tabela8[[#This Row],[Valor Realizado]]-Tabela8[[#This Row],[Valor Orçado]] -> -374833 | E7: =ABS((Tabela8[[#This Row],[Valor Realizado]]-Tabela8[[#This Row],[Valor Orçado]])/Tabela8[[#This Row],[Valor Orçado]]) -> 0.031438484 | H7: 999040128 | I7: Venda de TV LED 32' | J7: =SUMIF('Orçado Adptado'!B:B,ORÇAMENTO!H7,'Orçado Adptado'!C:C) -> 7594408 | K7: =SUMIF(Realizado!B:B,ORÇAMENTO!H7,Realizado!C:C) -> 5688659 | L7: =K7-J7 -> -1905749 | M7: =ABS((K7-J7)/J7) -> 0.25094109
A8: 43647 | B8: =SUMIF('Orçado Adptado'!A:A,Tabela8[[#This Row],[Mês/Ano]],'Orçado Adptado'!C:C) -> 12505746 | C8: =SUMIF(Realizado!A:A,Tabela8[[#This Row],[Mês/Ano]],Realizado!C:C) -> 13221807 | D8: =Tabela8[[#This Row],[Valor Realizado]]-Tabela8[[#This Row],[Valor Orçado]] -> 716061 | E8: =ABS((Tabela8[[#This Row],[Valor Realizado]]-Tabela8[[#This Row],[Valor Orçado]])/Tabela8[[#This Row],[Valor Orçado]]) -> 0.057258559 | H8: 999095851 | I8: Venda de Inspiron 15 | J8: =SUMIF('Orçado Adptado'!B:B,ORÇAMENTO!H8,'Orçado Adptado'!C:C) -> 6232625 | K8: =SUMIF(Realizado!B:B,ORÇAMENTO!H8,Realizado!C:C) -> 7829374 | L8: =K8-J8 -> 1596749 | M8: =ABS((K8-J8)/J8) -> 0.25619205
A9: 43678 | B9: =SUMIF('Orçado Adptado'!A:A,Tabela8[[#This Row],[Mês/Ano]],'Orçado Adptado'!C:C) -> 11962102 | C9: =SUMIF(Realizado!A:A,Tabela8[[#This Row],[Mês/Ano]],Realizado!C:C) -> 13099542 | D9: =Tabela8[[#This Row],[Valor Realizado]]-Tabela8[[#This Row],[Valor Orçado]] -> 1137440 | E9: =ABS((Tabela8[[#This Row],[Valor Realizado]]-Tabela8[[#This Row],[Valor Orçado]])/Tabela8[[#This Row],[Valor Orçado]]) -> 0.095086967 | H9: 999081468 | I9: Venda de Smart TV LED Full HD 55' | J9: =SUMIF('Orçado Adptado'!B:B,ORÇAMENTO!H9,'Orçado Adptado'!C:C) -> 7134223 | K9: =SUMIF(Realizado!B:B,ORÇAMENTO!H9,Realizado!C:C) -> 7931061 | L9: =K9-J9 -> 796838 | M9: =ABS((K9-J9)/J9) -> 0.11169233
A10: 43709 | B10: =SUMIF('Orçado Adptado'!A:A,Tabela8[[#This Row],[Mês/Ano]],'Orçado Adptado'!C:C) -> 11825071 | C10: =SUMIF(Realizado!A:A,Tabela8[[#This Row],[Mês/Ano]],Realizado!C:C) -> 13211336 | D10: =Tabela8[[#This Row],[Valor Realizado]]-Tabela8[[#This Row],[Valor Orçado]] -> 1386265 | E10: =ABS((Tabela8[[#This Row],[Valor Realizado]]-Tabela8[[#This Row],[Valor Orçado]])/Tabela8[[#This Row],[Valor Orçado]]) -> 0.11723101 | H10: 999072838 | I10: Venda de Moto G7 | J10: =SUMIF('Orçado Adptado'!B:B,ORÇAMENTO!H10,'Orçado Adptado'!C:C) -> 8554262 | K10: =SUMIF(Realizado!B:B,ORÇAMENTO!H10,Realizado!C:C) -> 8713680 | L10: =K10-J10 -> 159418 | M10: =ABS((K10-J10)/J10) -> 0.01863609
A11: 43739 | B11: =SUMIF('Orçado Adptado'!A:A,Tabela8[[#This Row],[Mês/Ano]],'Orçado Adptado'!C:C) -> 12795046 | C11: =SUMIF(Realizado!A:A,Tabela8[[#This Row],[Mês/Ano]],Realizado!C:C) -> 11359347 | D11: =Tabela8[[#This Row],[Valor Realizado]]-Tabela8[[#This Row],[Valor Orçado]] -> -1435699 | E11: =ABS((Tabela8[[#This Row],[Valor Realizado]]-Tabela8[[#This Row],[Valor Orçado]])/Tabela8[[#This Row],[Valor Orçado]]) -> 0.11220741 | H11: 999170260 | I11: Venda de iPhone 6S | J11: =SUMIF('Orçado Adptado'!B:B,ORÇAMENTO!H11,'Orçado Adptado'!C:C) -> 6650891 | K11: =SUMIF(Realizado!B:B,ORÇAMENTO!H11,Realizado!C:C) -> 7741927 | L11: =K11-J11 -> 1091036 | M11: =ABS((K11-J11)/J11) -> 0.16404358
A12: 43770 | B12: =SUMIF('Orçado Adptado'!A:A,Tabela8[[#This Row],[Mês/Ano]],'Orçado Adptado'!C:C) -> 12884065 | C12: =SUMIF(Realizado!A:A,Tabela8[[#This Row],[Mês/Ano]],Realizado!C:C) -> 11359053 | D12: =Tabela8[[#This Row],[Valor Realizado]]-Tabela8[[#This Row],[Valor Orçado]] -> -1525012 | E12: =ABS((Tabela8[[#This Row],[Valor Realizado]]-Tabela8[[#This Row],[Valor Orçado]])/Tabela8[[#This Row],[Valor Orçado]]) -> 0.1183642 | H12: 999090462 | I12: Venda de Tablet M10 Android | J12: =SUMIF('Orçado Adptado'!B:B,ORÇAMENTO!H12,'Orçado Adptado'!C:C) -> 7915502 | K12: =SUMIF(Realizado!B:B,ORÇAMENTO!H12,Realizado!C:C) -> 7094319 | L12: =K12-J12 -> -821183 | M12: =ABS((K12-J12)/J12) -> 0.10374364
A13: 43800 | B13: =SUMIF('Orçado Adptado'!A:A,Tabela8[[#This Row],[Mês/Ano]],'Orçado Adptado'!C:C) -> 11966732 | C13: =SUMIF(Realizado!A:A,Tabela8[[#This Row],[Mês/Ano]],Realizado!C:C) -> 13054144 | D13: =Tabela8[[#This Row],[Valor Realizado]]-Tabela8[[#This Row],[Valor Orçado]] -> 1087412 | E13: =ABS((Tabela8[[#This Row],[Valor Realizado]]-Tabela8[[#This Row],[Valor Orçado]])/Tabela8[[#This Row],[Valor Orçado]]) -> 0.090869587 | H13: 999106286 | I13: Venda de Dell G7 | J13: =SUMIF('Orçado Adptado'!B:B,ORÇAMENTO!H13,'Orçado Adptado'!C:C) -> 7527687 | K13: =SUMIF(Realizado!B:B,ORÇAMENTO!H13,Realizado!C:C) -> 7409118 | L13: =K13-J13 -> -118569 | M13: =ABS((K13-J13)/J13) -> 0.015751053
H14: 999165933 | I14: Venda de Câmera Coolpix L340 | J14: =SUMIF('Orçado Adptado'!B:B,ORÇAMENTO!H14,'Orçado Adptado'!C:C) -> 7706120 | K14: =SUMIF(Realizado!B:B,ORÇAMENTO!H14,Realizado!C:C) -> 7262511 | L14: =K14-J14 -> -443609 | M14: =ABS((K14-J14)/J14) -> 0.057565805
H15: 999042333 | I15: Venda de Galaxy J8 | J15: =SUMIF('Orçado Adptado'!B:B,ORÇAMENTO!H15,'Orçado Adptado'!C:C) -> 8324743 | K15: =SUMIF(Realizado!B:B,ORÇAMENTO!H15,Realizado!C:C) -> 7158168 | L15: =K15-J15 -> -1166575 | M15: =ABS((K15-J15)/J15) -> 0.14013346
H16: 999056853 | I16: Venda de Câmera Digital Sony Cyber | J16: =SUMIF('Orçado Adptado'!B:B,ORÇAMENTO!H16,'Orçado Adptado'!C:C) -> 8098517 | K16: =SUMIF(Realizado!B:B,ORÇAMENTO!H16,Realizado!C:C) -> 7774405 | L16: =K16-J16 -> -324112 | M16: =ABS((K16-J16)/J16) -> 0.040021154
H17: 999197804 | I17: Venda de Smart Watch Galaxy | J17: =SUMIF('Orçado Adptado'!B:B,ORÇAMENTO!H17,'Orçado Adptado'!C:C) -> 7112294 | K17: =SUMIF(Realizado!B:B,ORÇAMENTO!H17,Realizado!C:C) -> 7466015 | L17: =K17-J17 -> 353721 | M17: =ABS((K17-J17)/J17) -> 0.049733743
H18: 999120746 | I18: Venda de Smart TV 75' 4K | J18: =SUMIF('Orçado Adptado'!B:B,ORÇAMENTO!H18,'Orçado Adptado'!C:C) -> 7826055 | K18: =SUMIF(Realizado!B:B,ORÇAMENTO!H18,Realizado!C:C) -> 8340122 | L18: =K18-J18 -> 514067 | M18: =ABS((K18-J18)/J18) -> 0.065686607
H19: 999080229 | I19: Venda de Smart Watch MI | J19: =SUMIF('Orçado Adptado'!B:B,ORÇAMENTO!H19,'Orçado Adptado'!C:C) -> 7880447 | K19: =SUMIF(Realizado!B:B,ORÇAMENTO!H19,Realizado!C:C) -> 7559250 | L19: =K19-J19 -> -321197 | M19: =ABS((K19-J19)/J19) -> 0.040758729
H20: 999099884 | I20: Venda de iPhone XS | J20: =SUMIF('Orçado Adptado'!B:B,ORÇAMENTO!H20,'Orçado Adptado'!C:C) -> 6755183 | K20: =SUMIF(Realizado!B:B,ORÇAMENTO!H20,Realizado!C:C) -> 6559192 | L20: =K20-J20 -> -195991 | M20: =ABS((K20-J20)/J20) -> 0.029013426
H21: 999186602 | I21: Venda de Moto Z | J21: =SUMIF('Orçado Adptado'!B:B,ORÇAMENTO!H21,'Orçado Adptado'!C:C) -> 7038930 | K21: =SUMIF(Realizado!B:B,ORÇAMENTO!H21,Realizado!C:C) -> 6918743 | L21: =K21-J21 -> -120187 | M21: =ABS((K21-J21)/J21) -> 0.017074612
H22: 999065765 | I22: Venda de Galaxy S8 | J22: =SUMIF('Orçado Adptado'!B:B,ORÇAMENTO!H22,'Orçado Adptado'!C:C) -> 7735691 | K22: =SUMIF(Realizado!B:B,ORÇAMENTO!H22,Realizado!C:C) -> 6837973 | L22: =K22-J22 -> -897718 | M22: =ABS((K22-J22)/J22) -> 0.11604884
H23: 999051933 | I23: Venda de iPad 32GB Wifi | J23: =SUMIF('Orçado Adptado'!B:B,ORÇAMENTO!H23,'Orçado Adptado'!C:C) -> 7854881 | K23: =SUMIF(Realizado!B:B,ORÇAMENTO!H23,Realizado!C:C) -> 7152703 | L23: =K23-J23 -> -702178 | M23: =ABS((K23-J23)/J23) -> 0.089393843
H24: 999115414 | I24: Venda de Samsung Dual Core | J24: =SUMIF('Orçado Adptado'!B:B,ORÇAMENTO!H24,'Orçado Adptado'!C:C) -> 2327733 | K24: =SUMIF(Realizado!B:B,ORÇAMENTO!H24,Realizado!C:C) -> 2104190 | L24: =K24-J24 -> -223543 | M24: =ABS((K24-J24)/J24) -> 0.09603464
H25: 999179386 | I25: Venda de Aspire 5 | J25: =SUMIF('Orçado Adptado'!B:B,ORÇAMENTO!H25,'Orçado Adptado'!C:C) -> 2389903 | K25: =SUMIF(Realizado!B:B,ORÇAMENTO!H25,Realizado!C:C) -> 1952827 | L25: =K25-J25 -> -437076 | M25: =ABS((K25-J25)/J25) -> 0.18288441

Sheet RESUMO
A1: LUCRO LÍQUIDO MENSAL | D1: DESVIO ABSOLUTO DA RECEITA | H1: PRODUTOS MAIS VENDIDOS
A3: MÊS | B3: SOMA LUCRO LÍQUIDO MENSAL | D3: Rótulos de Linha | E3: Soma de Valor Orçado | F3: Soma de Valor Realizado | H3: Rótulos de Linha | I3: Soma de Valor Realizado
A4: jan | B4: 11641038 | D4: jan | E4: 12628342 | F4: 11641038 | H4: Venda de Apple Watch | I4: 8291974
A5: fev | B5: 11031445 | D5: fev | E5: 12787711 | F5: 11031445 | H5: Venda de Aspire 5 | I5: 1952827
A6: mar | B6: 12978938 | D6: mar | E6: 14186373 | F6: 12978938 | H6: Venda de Câmera Coolpix L340 | I6: 7262511
A7: abr | B7: 12589377 | D7: abr | E7: 9555695 | F7: 12589377 | H7: Venda de Câmera Digital Rebel T6 | I7: 8563185
A8: mai | B8: 8509153 | D8: mai | E8: 11240344 | F8: 8509153 | H8: Venda de Câmera Digital Sony Cyber | I8: 7774405
A9: jun | B9: 11547911 | D9: jun | E9: 11922744 | F9: 11547911 | H9: Venda de Dell G7 | I9: 7409118
A10: jul | B10: 13221807 | D10: jul | E10: 12505746 | F10: 13221807 | H10: Venda de Galaxy J8 | I10: 7158168
A11: ago | B11: 13099542 | D11: ago | E11: 11962102 | F11: 13099542 | H11: Venda de Galaxy S10 | I11: 7368112
A12: set | B12: 13211336 | D12: set | E12: 11825071 | F12: 13211336 | H12: Venda de Galaxy S8 | I12: 6837973
A13: out | B13: 11359347 | D13: out | E13: 12795046 | F13: 11359347 | H13: Venda de Inspiron 15 | I13: 7829374
A14: nov | B14: 11359053 | D14: nov | E14: 12884065 | F14: 11359053 | H14: Venda de iPad 32GB Wifi | I14: 7152703
A15: dez | B15: 13054144 | D15: dez | E15: 11966732 | F15: 13054144 | H15: Venda de iPhone 6S | I15: 7741927
H16: Venda de iPhone 7 | I16: 7768159
H17: Venda de iPhone XS | I17: 6559192
H18: Venda de Moto G7 | I18: 8713680
H19: Venda de Moto Z | I19: 6918743
H20: Venda de Samsung Dual Core | I20: 2104190
H21: Venda de Smart TV 50' 4K | I21: 7791574
H22: Venda de Smart TV 75' 4K | I22: 8340122
H23: Venda de Smart TV LED Full HD 55' | I23: 7931061
H24: Venda de Smart Watch Galaxy | I24: 7466015
H25: Venda de Smart Watch MI | I25: 7559250
H26: Venda de Tablet M10 Android | I26: 7094319
H27: Venda de TV LED 32' | I27: 5688659
H28: Total Geral | I28: 169277241
